spotify_lyrics_cli/__init__.py
spotify_lyrics_cli-0.1.data/scripts/lyrics-cli
spotify_lyrics_cli-0.1.dist-info/METADATA
spotify_lyrics_cli-0.1.dist-info/WHEEL
spotify_lyrics_cli-0.1.dist-info/top_level.txt
spotify_lyrics_cli-0.1.dist-info/RECORD
